[
  { "id": 1, "no": "26/03/12-1", "customer": "삼촌네푸줏간", "items": "우레탄판넬회색스타코 [4500*3000*2400] 외 11건", "total": 10700000, "payment": "", "drawing": true, "accounting": true, "printed": true, "ref": "한남냉동테크(주)", "date": "2026-03-12", "status": "완료" },
  { "id": 2, "no": "26/03/10-1", "customer": "주식회사알찬", "items": "우레탄판넬 냉동체슬건조기 [2평형]", "total": 11000000, "payment": "입금 부가세포함 완불", "drawing": true, "accounting": true, "printed": true, "ref": "한남냉동테크(주)", "date": "2026-03-10", "status": "입금완불" },
  { "id": 3, "no": "26/03/05-2", "customer": "(주)그린비전", "items": "우레탄판넬 회색스타코 [3000*2500*2200] 외 9건", "total": 6160000, "payment": "", "drawing": true, "accounting": true, "printed": true, "ref": "한남냉동테크(주)", "date": "2026-03-05", "status": "완료" },
  { "id": 4, "no": "26/03/05-1", "customer": "양평종합주방", "items": "팽창변 [냉동냉장 각1개씩] 외 1건", "total": 1047666, "payment": "입금완불", "drawing": true, "accounting": true, "printed": true, "ref": "한남냉동테크(주)", "date": "2026-03-05", "status": "입금완불" },
  { "id": 5, "no": "26/02/09-1", "customer": "주식회사사진로우성물산", "items": "충발기히터, 드레인교체 [식] 외 3건", "total": 2596000, "payment": "", "drawing": true, "accounting": true, "printed": true, "ref": "한남냉동테크(주)", "date": "2026-02-09", "status": "완료" },
  { "id": 6, "no": "26/02/02-1", "customer": "뮤지엄B", "items": "우레탄판넬 (회색스타코) [3000*2700*2500] 외 3건", "total": 2557830, "payment": "", "drawing": true, "accounting": true, "printed": false, "ref": "한남냉동테크(주)", "date": "2026-02-02", "status": "발송" },
  { "id": 7, "no": "26/01/27-2", "customer": "주식회사사진로우성물산", "items": "콤프레사 냉동 [30HP 2단 교체] 외 3건", "total": 10340000, "payment": "계약금 5,000,000원 1/26일", "drawing": true, "accounting": true, "printed": true, "ref": "한남냉동테크(주)", "date": "2026-01-27", "status": "완료" },
  { "id": 8, "no": "26/01/27-1", "customer": "양평종합주방", "items": "엑셀쿨러 히타선 [7.5hp*3p]", "total": 48400, "payment": "", "drawing": true, "accounting": true, "printed": true, "ref": "한남냉동테크(주)", "date": "2026-01-27", "status": "완료" },
  { "id": 9, "no": "26/01/26-1", "customer": "세방건설(주)", "items": "냉동기자재납품 [8000*4000*2600]", "total": 12100000, "payment": "", "drawing": true, "accounting": true, "printed": true, "ref": "한남냉동테크(주)", "date": "2026-01-26", "status": "완료" },
  { "id": 10, "no": "26/01/14-1", "customer": "세방건설(주)", "items": "냉동기 납품 [7.5hp, 쿨러10hp]", "total": 5500000, "payment": "", "drawing": true, "accounting": true, "printed": true, "ref": "한남냉동테크(주)", "date": "2026-01-14", "status": "완료" },
  { "id": 11, "no": "26/01/12-2", "customer": "주식회사명일앰에스", "items": "회색스타코 바닥 [11800*4270*100] 외 2건", "total": 4905077, "payment": "", "drawing": true, "accounting": true, "printed": true, "ref": "한남냉동테크(주)", "date": "2026-01-12", "status": "완료" },
  { "id": 12, "no": "26/01/12-1", "customer": "주식회사명일앰에스", "items": "우레탄판넬 [11800*2470*100T] 외 2건", "total": 4905077, "payment": "", "drawing": false, "accounting": true, "printed": true, "ref": "한남냉동테크(주)", "date": "2026-01-12", "status": "완료" },
  { "id": 13, "no": "26/01/07-1", "customer": "주성공조", "items": "우레탄판넬(회색스타코) [2200*2200*1900] 외 2건", "total": 974050, "payment": "", "drawing": true, "accounting": true, "printed": true, "ref": "한남냉동테크(주)", "date": "2026-01-07", "status": "완료" },
  { "id": 14, "no": "25/12/29-1", "customer": "에어렉스 용인대리점", "items": "우레탄판넬 레자엠보 [2080*2700*2400] 외 6건", "total": 1966123, "payment": "", "drawing": true, "accounting": true, "printed": true, "ref": "한남냉동테크(주)", "date": "2025-12-29", "status": "완료" },
  { "id": 15, "no": "25/12/26-1", "customer": "동남냉열가전주방", "items": "경첩 [k-702]", "total": 38500, "payment": "경첩 1셋트 입금완불", "drawing": true, "accounting": true, "printed": true, "ref": "한남냉동테크(주)", "date": "2025-12-26", "status": "입금완불" }
]
